method_flowchart/__init__.py
method_flowchart/analyzer.py
method_flowchart/cli.py
method_flowchart/decorator.py
method_flowchart/generator.py
method_flowchart/utils.py
tests/__init__.py
tests/test.py
tests/test_method_flowchart.py
method_flowchart-0.1.0.dist-info/METADATA
method_flowchart-0.1.0.dist-info/WHEEL
method_flowchart-0.1.0.dist-info/entry_points.txt
method_flowchart-0.1.0.dist-info/top_level.txt
method_flowchart-0.1.0.dist-info/RECORD
