Metadata-Version: 2.4
Name: method_flowchart
Version: 0.1.0
Summary: Generate Mermaid flowcharts from Python methods
Home-page: 
Author: Vipul Malhotra
Author-email: vipulm124@gmail.com
Keywords: mermaid flowchart ast code analysis documentation
Classifier: Programming Language :: Python :: 3
Classifier: License :: OSI Approved :: MIT License
Classifier: Operating System :: OS Independent
Classifier: Intended Audience :: Developers
Classifier: Topic :: Software Development :: Code Generators
Classifier: Topic :: Software Development :: Documentation
Dynamic: author
Dynamic: author-email
Dynamic: classifier
Dynamic: description
Dynamic: description-content-type
Dynamic: keywords
Dynamic: summary
